{"1": {"scores": [{"target": 50, "year": "2013", "score": 85}, {"target": 55, "year": "2014", "score": 70}, {"target": 60, "year": "2015", "score": 64}, {"target": 60, "year": "2016", "score": 56}]}, "3": {"scores": [{"target": 55, "year": "2013", "score": 81}, {"target": 28, "year": "2014", "score": 39}, {"target": 28, "year": "2015", "score": 37}, {"target": 28, "year": "2016", "score": 29}]}, "2": {"scores": [{"target": 30, "year": "2013", "score": 39}, {"target": 33, "year": "2014", "score": 39}, {"target": 30, "year": "2015", "score": 35}, {"target": 32, "year": "2016", "score": 27}]}, "4": {"scores": [{"target": 75, "year": "2013", "score": null}, {"target": 12, "year": "2014", "score": 14}, {"target": 12, "year": "2015", "score": 9}, {"target": 12, "year": "2016", "score": 10}]}, "name": "AUDRE AND BERNARD RAPOPORT ACADEMY", "dist_name": "RAPOPORT ACADEMY PUBLIC SCHOOL", "ratings": [{"rating": "M", "year": "2013"}, {"rating": "M", "year": "2014"}, {"rating": "I", "year": "2015"}, {"rating": "I", "year": "2016"}]}