{"1": {"scores": [{"target": 50, "year": "2013", "score": 73}, {"target": 55, "year": "2014", "score": 72}, {"target": null, "year": "2015", "score": null}, {"target": null, "year": "2016", "score": null}]}, "3": {"scores": [{"target": 55, "year": "2013", "score": 84}, {"target": 31, "year": "2014", "score": 35}, {"target": null, "year": "2015", "score": null}, {"target": null, "year": "2016", "score": null}]}, "2": {"scores": [{"target": 29, "year": "2013", "score": 30}, {"target": null, "year": "2014", "score": null}, {"target": null, "year": "2015", "score": null}, {"target": null, "year": "2016", "score": null}]}, "4": {"scores": [{"target": 75, "year": "2013", "score": null}, {"target": 21, "year": "2014", "score": 27}, {"target": null, "year": "2015", "score": null}, {"target": null, "year": "2016", "score": null}]}, "name": "UPLIFT EDUCATION - LAUREATE PREP S", "dist_name": "UPLIFT EDUCATION-SUMMIT INTERNATIO", "ratings": [{"rating": "M", "year": "2013"}, {"rating": "M", "year": "2014"}, {"rating": null, "year": "2015"}, {"rating": null, "year": "2016"}]}